pa_api/__init__.py
pa_api/constants.py
pa_api/panorama.py
pa_api/restapi/__init__.py
pa_api/restapi/rest_resources.py
pa_api/restapi/restapi.py
pa_api/utils.py
pa_api/xmlapi/__init__.py
pa_api/xmlapi/async_result.py
pa_api/xmlapi/base.py
pa_api/xmlapi/client.py
pa_api/xmlapi/clients/__init__.py
pa_api/xmlapi/clients/base.py
pa_api/xmlapi/clients/client.py
pa_api/xmlapi/clients/commit.py
pa_api/xmlapi/clients/config.py
pa_api/xmlapi/clients/logs.py
pa_api/xmlapi/clients/misc.py
pa_api/xmlapi/clients/operations/__init__.py
pa_api/xmlapi/clients/operations/base.py
pa_api/xmlapi/clients/operations/config.py
pa_api/xmlapi/clients/operations/ha.py
pa_api/xmlapi/clients/operations/job.py
pa_api/xmlapi/clients/operations/lock.py
pa_api/xmlapi/clients/operations/operation.py
pa_api/xmlapi/constants.py
pa_api/xmlapi/exceptions.py
pa_api/xmlapi/objects.py
pa_api/xmlapi/types/__init__.py
pa_api/xmlapi/types/config/__init__.py
pa_api/xmlapi/types/config/address.py
pa_api/xmlapi/types/config/config.py
pa_api/xmlapi/types/config/devicegroup.py
pa_api/xmlapi/types/config/interface.py
pa_api/xmlapi/types/config/profiles/__init__.py
pa_api/xmlapi/types/config/profiles/custom_url_category.py
pa_api/xmlapi/types/config/profiles/profile.py
pa_api/xmlapi/types/config/routing/__init__.py
pa_api/xmlapi/types/config/routing/routing_table.py
pa_api/xmlapi/types/config/rules/__init__.py
pa_api/xmlapi/types/config/rules/nat.py
pa_api/xmlapi/types/config/rules/rulebase.py
pa_api/xmlapi/types/config/rules/security.py
pa_api/xmlapi/types/config/zone.py
pa_api/xmlapi/types/logs/__init__.py
pa_api/xmlapi/types/logs/job.py
pa_api/xmlapi/types/operations/__init__.py
pa_api/xmlapi/types/operations/device.py
pa_api/xmlapi/types/operations/edl.py
pa_api/xmlapi/types/operations/ha.py
pa_api/xmlapi/types/operations/job.py
pa_api/xmlapi/types/operations/software.py
pa_api/xmlapi/types/operations/system.py
pa_api/xmlapi/types/statistics.py
pa_api/xmlapi/types/utils.py
pa_api/xmlapi/utils.py
pa_api_sdk-0.1.11.dist-info/LICENSE
pa_api_sdk-0.1.11.dist-info/METADATA
pa_api_sdk-0.1.11.dist-info/WHEEL
pa_api_sdk-0.1.11.dist-info/RECORD
