Metadata-Version: 2.3
Name: pa-api-sdk
Version: 0.1.11
Summary: 
Author: David Gallay
Author-email: david.gallay.96@gmail.com
Requires-Python: >=3.7.0,<4.0.0
Classifier: Programming Language :: Python :: 3
Classifier: Programming Language :: Python :: 3.7
Classifier: Programming Language :: Python :: 3.8
Classifier: Programming Language :: Python :: 3.9
Classifier: Programming Language :: Python :: 3.10
Classifier: Programming Language :: Python :: 3.11
Classifier: Programming Language :: Python :: 3.12
Classifier: Programming Language :: Python :: 3.13
Requires-Dist: lxml (>=4.9.3,<5.0.0)
Requires-Dist: pan-os-python (>=1.11.0,<2.0.0)
Requires-Dist: pydantic (>=2.5.3,<3.0.0)
Requires-Dist: requests (>=2.31.0,<3.0.0)
Requires-Dist: xmltodict (>=0.13.0,<0.14.0)
